odoo8_addon_l10n_id_taxform_employee_joining_period-8.0.1.0.0-py2.7-nspkg.pth
odoo_addons/l10n_id_taxform_employee_joining_period/__openerp__.py
odoo_addons/l10n_id_taxform_employee_joining_period/__init__.py
odoo_addons/l10n_id_taxform_employee_joining_period/README.rst
odoo_addons/l10n_id_taxform_employee_joining_period/models/hr_employee.py
odoo_addons/l10n_id_taxform_employee_joining_period/models/__init__.py
odoo_addons/l10n_id_taxform_employee_joining_period/views/hr_employee_views.xml
odoo_addons/l10n_id_taxform_employee_joining_period/tests/test_hr_employee.py
odoo_addons/l10n_id_taxform_employee_joining_period/tests/__init__.py
odoo_addons/l10n_id_taxform_employee_joining_period/static/description/icon.png
odoo8_addon_l10n_id_taxform_employee_joining_period-8.0.1.0.0.dist-info/top_level.txt
odoo8_addon_l10n_id_taxform_employee_joining_period-8.0.1.0.0.dist-info/WHEEL
odoo8_addon_l10n_id_taxform_employee_joining_period-8.0.1.0.0.dist-info/RECORD
odoo8_addon_l10n_id_taxform_employee_joining_period-8.0.1.0.0.dist-info/metadata.json
odoo8_addon_l10n_id_taxform_employee_joining_period-8.0.1.0.0.dist-info/DESCRIPTION.rst
odoo8_addon_l10n_id_taxform_employee_joining_period-8.0.1.0.0.dist-info/METADATA
odoo8_addon_l10n_id_taxform_employee_joining_period-8.0.1.0.0.dist-info/namespace_packages.txt
